logics/__init__.py
logics/__main__.py
logics/logics.py
logics/parser.py
logics/value.py
logics/version.py
logics_py-0.4.1.dist-info/METADATA
logics_py-0.4.1.dist-info/WHEEL
logics_py-0.4.1.dist-info/top_level.txt
logics_py-0.4.1.dist-info/RECORD
