Metadata-Version: 2.4
Name: logics-py
Version: 0.4.1
Summary: Logics is a user-friendly formula language with a subset of Python''s expression syntax
Home-page: https://github.com/viur-framework/logics
Author: Jan Max Meyer
Author-email: jmm@phorward.de
License: MIT
Classifier: Intended Audience :: Developers
Classifier: License :: OSI Approved :: MIT License
Classifier: Operating System :: OS Independent
Classifier: Programming Language :: Python :: 3.10
Classifier: Programming Language :: Python :: 3.11
Classifier: Programming Language :: Python :: 3.12
Classifier: Programming Language :: Python :: 3.13
Classifier: Topic :: Software Development :: Interpreters
Requires-Python: >=3.10
